{
  "type": "File",
  "start": 0,
  "end": 1152,
  "loc": {
    "start": {
      "line": 1,
      "column": 0
    },
    "end": {
      "line": 39,
      "column": 0
    }
  },
  "program": {
    "type": "Program",
    "start": 0,
    "end": 1152,
    "loc": {
      "start": {
        "line": 1,
        "column": 0
      },
      "end": {
        "line": 39,
        "column": 0
      }
    },
    "sourceType": "module",
    "body": [
      {
        "type": "ImportDeclaration",
        "start": 0,
        "end": 39,
        "loc": {
          "start": {
            "line": 1,
            "column": 0
          },
          "end": {
            "line": 1,
            "column": 39
          }
        },
        "specifiers": [
          {
            "type": "ImportDefaultSpecifier",
            "start": 7,
            "end": 16,
            "loc": {
              "start": {
                "line": 1,
                "column": 7
              },
              "end": {
                "line": 1,
                "column": 16
              }
            },
            "local": {
              "type": "Identifier",
              "start": 7,
              "end": 16,
              "loc": {
                "start": {
                  "line": 1,
                  "column": 7
                },
                "end": {
                  "line": 1,
                  "column": 16
                },
                "identifierName": "Equipment"
              },
              "name": "Equipment"
            }
          }
        ],
        "source": {
          "type": "StringLiteral",
          "start": 22,
          "end": 38,
          "loc": {
            "start": {
              "line": 1,
              "column": 22
            },
            "end": {
              "line": 1,
              "column": 38
            }
          },
          "extra": {
            "rawValue": "./equipment.js",
            "raw": "'./equipment.js'"
          },
          "value": "./equipment.js"
        }
      },
      {
        "type": "ImportDeclaration",
        "start": 40,
        "end": 99,
        "loc": {
          "start": {
            "line": 2,
            "column": 0
          },
          "end": {
            "line": 2,
            "column": 59
          }
        },
        "specifiers": [
          {
            "type": "ImportDefaultSpecifier",
            "start": 47,
            "end": 62,
            "loc": {
              "start": {
                "line": 2,
                "column": 7
              },
              "end": {
                "line": 2,
                "column": 22
              }
            },
            "local": {
              "type": "Identifier",
              "start": 47,
              "end": 62,
              "loc": {
                "start": {
                  "line": 2,
                  "column": 7
                },
                "end": {
                  "line": 2,
                  "column": 22
                },
                "identifierName": "ItemsDictionary"
              },
              "name": "ItemsDictionary"
            }
          }
        ],
        "source": {
          "type": "StringLiteral",
          "start": 68,
          "end": 98,
          "loc": {
            "start": {
              "line": 2,
              "column": 28
            },
            "end": {
              "line": 2,
              "column": 58
            }
          },
          "extra": {
            "rawValue": "../../../../../util/items.js",
            "raw": "'../../../../../util/items.js'"
          },
          "value": "../../../../../util/items.js"
        },
        "trailingComments": [
          {
            "type": "CommentBlock",
            "value": "*\n * Represents a pendant equipment item worn by the player\n * @class\n ",
            "start": 101,
            "end": 176,
            "loc": {
              "start": {
                "line": 4,
                "column": 0
              },
              "end": {
                "line": 7,
                "column": 3
              }
            }
          }
        ]
      },
      {
        "type": "ExportDefaultDeclaration",
        "start": 177,
        "end": 1151,
        "loc": {
          "start": {
            "line": 8,
            "column": 0
          },
          "end": {
            "line": 38,
            "column": 1
          }
        },
        "declaration": {
          "type": "ClassDeclaration",
          "start": 192,
          "end": 1151,
          "loc": {
            "start": {
              "line": 8,
              "column": 15
            },
            "end": {
              "line": 38,
              "column": 1
            }
          },
          "id": {
            "type": "Identifier",
            "start": 198,
            "end": 205,
            "loc": {
              "start": {
                "line": 8,
                "column": 21
              },
              "end": {
                "line": 8,
                "column": 28
              },
              "identifierName": "Pendant"
            },
            "name": "Pendant",
            "leadingComments": null
          },
          "superClass": {
            "type": "Identifier",
            "start": 214,
            "end": 223,
            "loc": {
              "start": {
                "line": 8,
                "column": 37
              },
              "end": {
                "line": 8,
                "column": 46
              },
              "identifierName": "Equipment"
            },
            "name": "Equipment"
          },
          "body": {
            "type": "ClassBody",
            "start": 224,
            "end": 1151,
            "loc": {
              "start": {
                "line": 8,
                "column": 47
              },
              "end": {
                "line": 38,
                "column": 1
              }
            },
            "body": [
              {
                "type": "ClassMethod",
                "start": 572,
                "end": 983,
                "loc": {
                  "start": {
                    "line": 17,
                    "column": 2
                  },
                  "end": {
                    "line": 29,
                    "column": 3
                  }
                },
                "static": false,
                "computed": false,
                "key": {
                  "type": "Identifier",
                  "start": 572,
                  "end": 583,
                  "loc": {
                    "start": {
                      "line": 17,
                      "column": 2
                    },
                    "end": {
                      "line": 17,
                      "column": 13
                    },
                    "identifierName": "constructor"
                  },
                  "name": "constructor",
                  "leadingComments": null
                },
                "kind": "constructor",
                "id": null,
                "generator": false,
                "expression": false,
                "async": false,
                "params": [
                  {
                    "type": "Identifier",
                    "start": 584,
                    "end": 588,
                    "loc": {
                      "start": {
                        "line": 17,
                        "column": 14
                      },
                      "end": {
                        "line": 17,
                        "column": 18
                      },
                      "identifierName": "name"
                    },
                    "name": "name"
                  },
                  {
                    "type": "Identifier",
                    "start": 590,
                    "end": 592,
                    "loc": {
                      "start": {
                        "line": 17,
                        "column": 20
                      },
                      "end": {
                        "line": 17,
                        "column": 22
                      },
                      "identifierName": "id"
                    },
                    "name": "id"
                  },
                  {
                    "type": "Identifier",
                    "start": 594,
                    "end": 599,
                    "loc": {
                      "start": {
                        "line": 17,
                        "column": 24
                      },
                      "end": {
                        "line": 17,
                        "column": 29
                      },
                      "identifierName": "count"
                    },
                    "name": "count"
                  },
                  {
                    "type": "Identifier",
                    "start": 601,
                    "end": 608,
                    "loc": {
                      "start": {
                        "line": 17,
                        "column": 31
                      },
                      "end": {
                        "line": 17,
                        "column": 38
                      },
                      "identifierName": "ability"
                    },
                    "name": "ability"
                  },
                  {
                    "type": "Identifier",
                    "start": 610,
                    "end": 622,
                    "loc": {
                      "start": {
                        "line": 17,
                        "column": 40
                      },
                      "end": {
                        "line": 17,
                        "column": 52
                      },
                      "identifierName": "abilityLevel"
                    },
                    "name": "abilityLevel"
                  }
                ],
                "body": {
                  "type": "BlockStatement",
                  "start": 624,
                  "end": 983,
                  "loc": {
                    "start": {
                      "line": 17,
                      "column": 54
                    },
                    "end": {
                      "line": 29,
                      "column": 3
                    }
                  },
                  "body": [
                    {
                      "type": "ExpressionStatement",
                      "start": 630,
                      "end": 676,
                      "loc": {
                        "start": {
                          "line": 18,
                          "column": 4
                        },
                        "end": {
                          "line": 18,
                          "column": 50
                        }
                      },
                      "expression": {
                        "type": "CallExpression",
                        "start": 630,
                        "end": 675,
                        "loc": {
                          "start": {
                            "line": 18,
                            "column": 4
                          },
                          "end": {
                            "line": 18,
                            "column": 49
                          }
                        },
                        "callee": {
                          "type": "Super",
                          "start": 630,
                          "end": 635,
                          "loc": {
                            "start": {
                              "line": 18,
                              "column": 4
                            },
                            "end": {
                              "line": 18,
                              "column": 9
                            }
                          }
                        },
                        "arguments": [
                          {
                            "type": "Identifier",
                            "start": 636,
                            "end": 640,
                            "loc": {
                              "start": {
                                "line": 18,
                                "column": 10
                              },
                              "end": {
                                "line": 18,
                                "column": 14
                              },
                              "identifierName": "name"
                            },
                            "name": "name"
                          },
                          {
                            "type": "Identifier",
                            "start": 642,
                            "end": 644,
                            "loc": {
                              "start": {
                                "line": 18,
                                "column": 16
                              },
                              "end": {
                                "line": 18,
                                "column": 18
                              },
                              "identifierName": "id"
                            },
                            "name": "id"
                          },
                          {
                            "type": "Identifier",
                            "start": 646,
                            "end": 651,
                            "loc": {
                              "start": {
                                "line": 18,
                                "column": 20
                              },
                              "end": {
                                "line": 18,
                                "column": 25
                              },
                              "identifierName": "count"
                            },
                            "name": "count"
                          },
                          {
                            "type": "Identifier",
                            "start": 653,
                            "end": 660,
                            "loc": {
                              "start": {
                                "line": 18,
                                "column": 27
                              },
                              "end": {
                                "line": 18,
                                "column": 34
                              },
                              "identifierName": "ability"
                            },
                            "name": "ability"
                          },
                          {
                            "type": "Identifier",
                            "start": 662,
                            "end": 674,
                            "loc": {
                              "start": {
                                "line": 18,
                                "column": 36
                              },
                              "end": {
                                "line": 18,
                                "column": 48
                              },
                              "identifierName": "abilityLevel"
                            },
                            "name": "abilityLevel"
                          }
                        ]
                      },
                      "trailingComments": [
                        {
                          "type": "CommentBlock",
                          "value": "*\n     * Reference to the items dictionary for stat lookups\n     * @type {Object}\n     ",
                          "start": 681,
                          "end": 772,
                          "loc": {
                            "start": {
                              "line": 19,
                              "column": 4
                            },
                            "end": {
                              "line": 22,
                              "column": 7
                            }
                          }
                        }
                      ]
                    },
                    {
                      "type": "ExpressionStatement",
                      "start": 777,
                      "end": 816,
                      "loc": {
                        "start": {
                          "line": 23,
                          "column": 4
                        },
                        "end": {
                          "line": 23,
                          "column": 43
                        }
                      },
                      "expression": {
                        "type": "AssignmentExpression",
                        "start": 777,
                        "end": 815,
                        "loc": {
                          "start": {
                            "line": 23,
                            "column": 4
                          },
                          "end": {
                            "line": 23,
                            "column": 42
                          }
                        },
                        "operator": "=",
                        "left": {
                          "type": "MemberExpression",
                          "start": 777,
                          "end": 797,
                          "loc": {
                            "start": {
                              "line": 23,
                              "column": 4
                            },
                            "end": {
                              "line": 23,
                              "column": 24
                            }
                          },
                          "object": {
                            "type": "ThisExpression",
                            "start": 777,
                            "end": 781,
                            "loc": {
                              "start": {
                                "line": 23,
                                "column": 4
                              },
                              "end": {
                                "line": 23,
                                "column": 8
                              }
                            },
                            "leadingComments": null
                          },
                          "property": {
                            "type": "Identifier",
                            "start": 782,
                            "end": 797,
                            "loc": {
                              "start": {
                                "line": 23,
                                "column": 9
                              },
                              "end": {
                                "line": 23,
                                "column": 24
                              },
                              "identifierName": "itemsDictionary"
                            },
                            "name": "itemsDictionary"
                          },
                          "computed": false,
                          "leadingComments": null
                        },
                        "right": {
                          "type": "Identifier",
                          "start": 800,
                          "end": 815,
                          "loc": {
                            "start": {
                              "line": 23,
                              "column": 27
                            },
                            "end": {
                              "line": 23,
                              "column": 42
                            },
                            "identifierName": "ItemsDictionary"
                          },
                          "name": "ItemsDictionary"
                        },
                        "leadingComments": null
                      },
                      "leadingComments": [
                        {
                          "type": "CommentBlock",
                          "value": "*\n     * Reference to the items dictionary for stat lookups\n     * @type {Object}\n     ",
                          "start": 681,
                          "end": 772,
                          "loc": {
                            "start": {
                              "line": 19,
                              "column": 4
                            },
                            "end": {
                              "line": 22,
                              "column": 7
                            }
                          }
                        }
                      ],
                      "trailingComments": [
                        {
                          "type": "CommentBlock",
                          "value": "*\n     * The pendant level used to calculate the amplifier\n     * @type {Number}\n     ",
                          "start": 821,
                          "end": 911,
                          "loc": {
                            "start": {
                              "line": 24,
                              "column": 4
                            },
                            "end": {
                              "line": 27,
                              "column": 7
                            }
                          }
                        }
                      ]
                    },
                    {
                      "type": "ExpressionStatement",
                      "start": 916,
                      "end": 979,
                      "loc": {
                        "start": {
                          "line": 28,
                          "column": 4
                        },
                        "end": {
                          "line": 28,
                          "column": 67
                        }
                      },
                      "expression": {
                        "type": "AssignmentExpression",
                        "start": 916,
                        "end": 978,
                        "loc": {
                          "start": {
                            "line": 28,
                            "column": 4
                          },
                          "end": {
                            "line": 28,
                            "column": 66
                          }
                        },
                        "operator": "=",
                        "left": {
                          "type": "MemberExpression",
                          "start": 916,
                          "end": 933,
                          "loc": {
                            "start": {
                              "line": 28,
                              "column": 4
                            },
                            "end": {
                              "line": 28,
                              "column": 21
                            }
                          },
                          "object": {
                            "type": "ThisExpression",
                            "start": 916,
                            "end": 920,
                            "loc": {
                              "start": {
                                "line": 28,
                                "column": 4
                              },
                              "end": {
                                "line": 28,
                                "column": 8
                              }
                            },
                            "leadingComments": null
                          },
                          "property": {
                            "type": "Identifier",
                            "start": 921,
                            "end": 933,
                            "loc": {
                              "start": {
                                "line": 28,
                                "column": 9
                              },
                              "end": {
                                "line": 28,
                                "column": 21
                              },
                              "identifierName": "pendantLevel"
                            },
                            "name": "pendantLevel"
                          },
                          "computed": false,
                          "leadingComments": null
                        },
                        "right": {
                          "type": "CallExpression",
                          "start": 936,
                          "end": 978,
                          "loc": {
                            "start": {
                              "line": 28,
                              "column": 24
                            },
                            "end": {
                              "line": 28,
                              "column": 66
                            }
                          },
                          "callee": {
                            "type": "MemberExpression",
                            "start": 936,
                            "end": 972,
                            "loc": {
                              "start": {
                                "line": 28,
                                "column": 24
                              },
                              "end": {
                                "line": 28,
                                "column": 60
                              }
                            },
                            "object": {
                              "type": "MemberExpression",
                              "start": 936,
                              "end": 956,
                              "loc": {
                                "start": {
                                  "line": 28,
                                  "column": 24
                                },
                                "end": {
                                  "line": 28,
                                  "column": 44
                                }
                              },
                              "object": {
                                "type": "ThisExpression",
                                "start": 936,
                                "end": 940,
                                "loc": {
                                  "start": {
                                    "line": 28,
                                    "column": 24
                                  },
                                  "end": {
                                    "line": 28,
                                    "column": 28
                                  }
                                }
                              },
                              "property": {
                                "type": "Identifier",
                                "start": 941,
                                "end": 956,
                                "loc": {
                                  "start": {
                                    "line": 28,
                                    "column": 29
                                  },
                                  "end": {
                                    "line": 28,
                                    "column": 44
                                  },
                                  "identifierName": "itemsDictionary"
                                },
                                "name": "itemsDictionary"
                              },
                              "computed": false
                            },
                            "property": {
                              "type": "Identifier",
                              "start": 957,
                              "end": 972,
                              "loc": {
                                "start": {
                                  "line": 28,
                                  "column": 45
                                },
                                "end": {
                                  "line": 28,
                                  "column": 60
                                },
                                "identifierName": "getPendantLevel"
                              },
                              "name": "getPendantLevel"
                            },
                            "computed": false
                          },
                          "arguments": [
                            {
                              "type": "Identifier",
                              "start": 973,
                              "end": 977,
                              "loc": {
                                "start": {
                                  "line": 28,
                                  "column": 61
                                },
                                "end": {
                                  "line": 28,
                                  "column": 65
                                },
                                "identifierName": "name"
                              },
                              "name": "name"
                            }
                          ]
                        },
                        "leadingComments": null
                      },
                      "leadingComments": [
                        {
                          "type": "CommentBlock",
                          "value": "*\n     * The pendant level used to calculate the amplifier\n     * @type {Number}\n     ",
                          "start": 821,
                          "end": 911,
                          "loc": {
                            "start": {
                              "line": 24,
                              "column": 4
                            },
                            "end": {
                              "line": 27,
                              "column": 7
                            }
                          }
                        }
                      ]
                    }
                  ],
                  "directives": [],
                  "trailingComments": null
                },
                "leadingComments": [
                  {
                    "type": "CommentBlock",
                    "value": "*\n   * Default constructor\n   * @param {String} name the name of the pendant\n   * @param {Number} id the item ID of the pendant\n   * @param {Number} count the enchantment level of the pendant\n   * @param {Number} ability the ability ID associated with this pendant\n   * @param {Number} abilityLevel the level of the pendant's ability\n   ",
                    "start": 228,
                    "end": 569,
                    "loc": {
                      "start": {
                        "line": 9,
                        "column": 2
                      },
                      "end": {
                        "line": 16,
                        "column": 5
                      }
                    }
                  }
                ],
                "trailingComments": [
                  {
                    "type": "CommentBlock",
                    "value": "*\n   * Returns the base stat amplifier provided by this pendant\n   * @return {Number}\n   ",
                    "start": 987,
                    "end": 1080,
                    "loc": {
                      "start": {
                        "line": 31,
                        "column": 2
                      },
                      "end": {
                        "line": 34,
                        "column": 5
                      }
                    }
                  }
                ]
              },
              {
                "type": "ClassMethod",
                "start": 1083,
                "end": 1149,
                "loc": {
                  "start": {
                    "line": 35,
                    "column": 2
                  },
                  "end": {
                    "line": 37,
                    "column": 3
                  }
                },
                "static": false,
                "computed": false,
                "key": {
                  "type": "Identifier",
                  "start": 1083,
                  "end": 1099,
                  "loc": {
                    "start": {
                      "line": 35,
                      "column": 2
                    },
                    "end": {
                      "line": 35,
                      "column": 18
                    },
                    "identifierName": "getBaseAmplifier"
                  },
                  "name": "getBaseAmplifier",
                  "leadingComments": null
                },
                "kind": "method",
                "id": null,
                "generator": false,
                "expression": false,
                "async": false,
                "params": [],
                "body": {
                  "type": "BlockStatement",
                  "start": 1102,
                  "end": 1149,
                  "loc": {
                    "start": {
                      "line": 35,
                      "column": 21
                    },
                    "end": {
                      "line": 37,
                      "column": 3
                    }
                  },
                  "body": [
                    {
                      "type": "ReturnStatement",
                      "start": 1108,
                      "end": 1145,
                      "loc": {
                        "start": {
                          "line": 36,
                          "column": 4
                        },
                        "end": {
                          "line": 36,
                          "column": 41
                        }
                      },
                      "argument": {
                        "type": "BinaryExpression",
                        "start": 1115,
                        "end": 1144,
                        "loc": {
                          "start": {
                            "line": 36,
                            "column": 11
                          },
                          "end": {
                            "line": 36,
                            "column": 40
                          }
                        },
                        "left": {
                          "type": "NumericLiteral",
                          "start": 1115,
                          "end": 1118,
                          "loc": {
                            "start": {
                              "line": 36,
                              "column": 11
                            },
                            "end": {
                              "line": 36,
                              "column": 14
                            }
                          },
                          "extra": {
                            "rawValue": 1,
                            "raw": "1.0"
                          },
                          "value": 1
                        },
                        "operator": "+",
                        "right": {
                          "type": "BinaryExpression",
                          "start": 1121,
                          "end": 1144,
                          "loc": {
                            "start": {
                              "line": 36,
                              "column": 17
                            },
                            "end": {
                              "line": 36,
                              "column": 40
                            }
                          },
                          "left": {
                            "type": "MemberExpression",
                            "start": 1121,
                            "end": 1138,
                            "loc": {
                              "start": {
                                "line": 36,
                                "column": 17
                              },
                              "end": {
                                "line": 36,
                                "column": 34
                              }
                            },
                            "object": {
                              "type": "ThisExpression",
                              "start": 1121,
                              "end": 1125,
                              "loc": {
                                "start": {
                                  "line": 36,
                                  "column": 17
                                },
                                "end": {
                                  "line": 36,
                                  "column": 21
                                }
                              }
                            },
                            "property": {
                              "type": "Identifier",
                              "start": 1126,
                              "end": 1138,
                              "loc": {
                                "start": {
                                  "line": 36,
                                  "column": 22
                                },
                                "end": {
                                  "line": 36,
                                  "column": 34
                                },
                                "identifierName": "pendantLevel"
                              },
                              "name": "pendantLevel"
                            },
                            "computed": false
                          },
                          "operator": "/",
                          "right": {
                            "type": "NumericLiteral",
                            "start": 1141,
                            "end": 1144,
                            "loc": {
                              "start": {
                                "line": 36,
                                "column": 37
                              },
                              "end": {
                                "line": 36,
                                "column": 40
                              }
                            },
                            "extra": {
                              "rawValue": 100,
                              "raw": "100"
                            },
                            "value": 100
                          }
                        }
                      }
                    }
                  ],
                  "directives": []
                },
                "leadingComments": [
                  {
                    "type": "CommentBlock",
                    "value": "*\n   * Returns the base stat amplifier provided by this pendant\n   * @return {Number}\n   ",
                    "start": 987,
                    "end": 1080,
                    "loc": {
                      "start": {
                        "line": 31,
                        "column": 2
                      },
                      "end": {
                        "line": 34,
                        "column": 5
                      }
                    }
                  }
                ]
              }
            ]
          },
          "leadingComments": [
            {
              "type": "CommentBlock",
              "value": "*\n * Represents a pendant equipment item worn by the player\n * @class\n ",
              "start": 101,
              "end": 176,
              "loc": {
                "start": {
                  "line": 4,
                  "column": 0
                },
                "end": {
                  "line": 7,
                  "column": 3
                }
              }
            }
          ],
          "trailingComments": []
        },
        "leadingComments": [
          {
            "type": "CommentBlock",
            "value": "*\n * Represents a pendant equipment item worn by the player\n * @class\n ",
            "start": 101,
            "end": 176,
            "loc": {
              "start": {
                "line": 4,
                "column": 0
              },
              "end": {
                "line": 7,
                "column": 3
              }
            }
          }
        ]
      }
    ],
    "directives": []
  },
  "comments": [
    {
      "type": "CommentBlock",
      "value": "*\n * Represents a pendant equipment item worn by the player\n * @class\n ",
      "start": 101,
      "end": 176,
      "loc": {
        "start": {
          "line": 4,
          "column": 0
        },
        "end": {
          "line": 7,
          "column": 3
        }
      }
    },
    {
      "type": "CommentBlock",
      "value": "*\n   * Default constructor\n   * @param {String} name the name of the pendant\n   * @param {Number} id the item ID of the pendant\n   * @param {Number} count the enchantment level of the pendant\n   * @param {Number} ability the ability ID associated with this pendant\n   * @param {Number} abilityLevel the level of the pendant's ability\n   ",
      "start": 228,
      "end": 569,
      "loc": {
        "start": {
          "line": 9,
          "column": 2
        },
        "end": {
          "line": 16,
          "column": 5
        }
      }
    },
    {
      "type": "CommentBlock",
      "value": "*\n     * Reference to the items dictionary for stat lookups\n     * @type {Object}\n     ",
      "start": 681,
      "end": 772,
      "loc": {
        "start": {
          "line": 19,
          "column": 4
        },
        "end": {
          "line": 22,
          "column": 7
        }
      }
    },
    {
      "type": "CommentBlock",
      "value": "*\n     * The pendant level used to calculate the amplifier\n     * @type {Number}\n     ",
      "start": 821,
      "end": 911,
      "loc": {
        "start": {
          "line": 24,
          "column": 4
        },
        "end": {
          "line": 27,
          "column": 7
        }
      }
    },
    {
      "type": "CommentBlock",
      "value": "*\n   * Returns the base stat amplifier provided by this pendant\n   * @return {Number}\n   ",
      "start": 987,
      "end": 1080,
      "loc": {
        "start": {
          "line": 31,
          "column": 2
        },
        "end": {
          "line": 34,
          "column": 5
        }
      }
    }
  ],
  "tokens": [
    {
      "type": {
        "label": "import",
        "keyword": "import",
        "beforeExpr": false,
        "startsExpr": true,
        "rightAssociative": false,
        "isLoop": false,
        "isAssign": false,
        "prefix": false,
        "postfix": false,
        "binop": null,
        "updateContext": null
      },
      "value": "import",
      "start": 0,
      "end": 6,
      "loc": {
        "start": {
          "line": 1,
          "column": 0
        },
        "end": {
          "line": 1,
          "column": 6
        }
      }
    },
    {
      "type": {
        "label": "name",
        "beforeExpr": false,
        "startsExpr": true,
        "rightAssociative": false,
        "isLoop": false,
        "isAssign": false,
        "prefix": false,
        "postfix": false,
        "binop": null
      },
      "value": "Equipment",
      "start": 7,
      "end": 16,
      "loc": {
        "start": {
          "line": 1,
          "column": 7
        },
        "end": {
          "line": 1,
          "column": 16
        }
      }
    },
    {
      "type": {
        "label": "name",
        "beforeExpr": false,
        "startsExpr": true,
        "rightAssociative": false,
        "isLoop": false,
        "isAssign": false,
        "prefix": false,
        "postfix": false,
        "binop": null
      },
      "value": "from",
      "start": 17,
      "end": 21,
      "loc": {
        "start": {
          "line": 1,
          "column": 17
        },
        "end": {
          "line": 1,
          "column": 21
        }
      }
    },
    {
      "type": {
        "label": "string",
        "beforeExpr": false,
        "startsExpr": true,
        "rightAssociative": false,
        "isLoop": false,
        "isAssign": false,
        "prefix": false,
        "postfix": false,
        "binop": null,
        "updateContext": null
      },
      "value": "./equipment.js",
      "start": 22,
      "end": 38,
      "loc": {
        "start": {
          "line": 1,
          "column": 22
        },
        "end": {
          "line": 1,
          "column": 38
        }
      }
    },
    {
      "type": {
        "label": ";",
        "beforeExpr": true,
        "startsExpr": false,
        "rightAssociative": false,
        "isLoop": false,
        "isAssign": false,
        "prefix": false,
        "postfix": false,
        "binop": null,
        "updateContext": null
      },
      "start": 38,
      "end": 39,
      "loc": {
        "start": {
          "line": 1,
          "column": 38
        },
        "end": {
          "line": 1,
          "column": 39
        }
      }
    },
    {
      "type": {
        "label": "import",
        "keyword": "import",
        "beforeExpr": false,
        "startsExpr": true,
        "rightAssociative": false,
        "isLoop": false,
        "isAssign": false,
        "prefix": false,
        "postfix": false,
        "binop": null,
        "updateContext": null
      },
      "value": "import",
      "start": 40,
      "end": 46,
      "loc": {
        "start": {
          "line": 2,
          "column": 0
        },
        "end": {
          "line": 2,
          "column": 6
        }
      }
    },
    {
      "type": {
        "label": "name",
        "beforeExpr": false,
        "startsExpr": true,
        "rightAssociative": false,
        "isLoop": false,
        "isAssign": false,
        "prefix": false,
        "postfix": false,
        "binop": null
      },
      "value": "ItemsDictionary",
      "start": 47,
      "end": 62,
      "loc": {
        "start": {
          "line": 2,
          "column": 7
        },
        "end": {
          "line": 2,
          "column": 22
        }
      }
    },
    {
      "type": {
        "label": "name",
        "beforeExpr": false,
        "startsExpr": true,
        "rightAssociative": false,
        "isLoop": false,
        "isAssign": false,
        "prefix": false,
        "postfix": false,
        "binop": null
      },
      "value": "from",
      "start": 63,
      "end": 67,
      "loc": {
        "start": {
          "line": 2,
          "column": 23
        },
        "end": {
          "line": 2,
          "column": 27
        }
      }
    },
    {
      "type": {
        "label": "string",
        "beforeExpr": false,
        "startsExpr": true,
        "rightAssociative": false,
        "isLoop": false,
        "isAssign": false,
        "prefix": false,
        "postfix": false,
        "binop": null,
        "updateContext": null
      },
      "value": "../../../../../util/items.js",
      "start": 68,
      "end": 98,
      "loc": {
        "start": {
          "line": 2,
          "column": 28
        },
        "end": {
          "line": 2,
          "column": 58
        }
      }
    },
    {
      "type": {
        "label": ";",
        "beforeExpr": true,
        "startsExpr": false,
        "rightAssociative": false,
        "isLoop": false,
        "isAssign": false,
        "prefix": false,
        "postfix": false,
        "binop": null,
        "updateContext": null
      },
      "start": 98,
      "end": 99,
      "loc": {
        "start": {
          "line": 2,
          "column": 58
        },
        "end": {
          "line": 2,
          "column": 59
        }
      }
    },
    {
      "type": "CommentBlock",
      "value": "*\n * Represents a pendant equipment item worn by the player\n * @class\n ",
      "start": 101,
      "end": 176,
      "loc": {
        "start": {
          "line": 4,
          "column": 0
        },
        "end": {
          "line": 7,
          "column": 3
        }
      }
    },
    {
      "type": {
        "label": "export",
        "keyword": "export",
        "beforeExpr": false,
        "startsExpr": false,
        "rightAssociative": false,
        "isLoop": false,
        "isAssign": false,
        "prefix": false,
        "postfix": false,
        "binop": null,
        "updateContext": null
      },
      "value": "export",
      "start": 177,
      "end": 183,
      "loc": {
        "start": {
          "line": 8,
          "column": 0
        },
        "end": {
          "line": 8,
          "column": 6
        }
      }
    },
    {
      "type": {
        "label": "default",
        "keyword": "default",
        "beforeExpr": true,
        "startsExpr": false,
        "rightAssociative": false,
        "isLoop": false,
        "isAssign": false,
        "prefix": false,
        "postfix": false,
        "binop": null,
        "updateContext": null
      },
      "value": "default",
      "start": 184,
      "end": 191,
      "loc": {
        "start": {
          "line": 8,
          "column": 7
        },
        "end": {
          "line": 8,
          "column": 14
        }
      }
    },
    {
      "type": {
        "label": "class",
        "keyword": "class",
        "beforeExpr": false,
        "startsExpr": false,
        "rightAssociative": false,
        "isLoop": false,
        "isAssign": false,
        "prefix": false,
        "postfix": false,
        "binop": null,
        "updateContext": null
      },
      "value": "class",
      "start": 192,
      "end": 197,
      "loc": {
        "start": {
          "line": 8,
          "column": 15
        },
        "end": {
          "line": 8,
          "column": 20
        }
      }
    },
    {
      "type": {
        "label": "name",
        "beforeExpr": false,
        "startsExpr": true,
        "rightAssociative": false,
        "isLoop": false,
        "isAssign": false,
        "prefix": false,
        "postfix": false,
        "binop": null
      },
      "value": "Pendant",
      "start": 198,
      "end": 205,
      "loc": {
        "start": {
          "line": 8,
          "column": 21
        },
        "end": {
          "line": 8,
          "column": 28
        }
      }
    },
    {
      "type": {
        "label": "extends",
        "keyword": "extends",
        "beforeExpr": true,
        "startsExpr": false,
        "rightAssociative": false,
        "isLoop": false,
        "isAssign": false,
        "prefix": false,
        "postfix": false,
        "binop": null,
        "updateContext": null
      },
      "value": "extends",
      "start": 206,
      "end": 213,
      "loc": {
        "start": {
          "line": 8,
          "column": 29
        },
        "end": {
          "line": 8,
          "column": 36
        }
      }
    },
    {
      "type": {
        "label": "name",
        "beforeExpr": false,
        "startsExpr": true,
        "rightAssociative": false,
        "isLoop": false,
        "isAssign": false,
        "prefix": false,
        "postfix": false,
        "binop": null
      },
      "value": "Equipment",
      "start": 214,
      "end": 223,
      "loc": {
        "start": {
          "line": 8,
          "column": 37
        },
        "end": {
          "line": 8,
          "column": 46
        }
      }
    },
    {
      "type": {
        "label": "{",
        "beforeExpr": true,
        "startsExpr": true,
        "rightAssociative": false,
        "isLoop": false,
        "isAssign": false,
        "prefix": false,
        "postfix": false,
        "binop": null
      },
      "start": 224,
      "end": 225,
      "loc": {
        "start": {
          "line": 8,
          "column": 47
        },
        "end": {
          "line": 8,
          "column": 48
        }
      }
    },
    {
      "type": "CommentBlock",
      "value": "*\n   * Default constructor\n   * @param {String} name the name of the pendant\n   * @param {Number} id the item ID of the pendant\n   * @param {Number} count the enchantment level of the pendant\n   * @param {Number} ability the ability ID associated with this pendant\n   * @param {Number} abilityLevel the level of the pendant's ability\n   ",
      "start": 228,
      "end": 569,
      "loc": {
        "start": {
          "line": 9,
          "column": 2
        },
        "end": {
          "line": 16,
          "column": 5
        }
      }
    },
    {
      "type": {
        "label": "name",
        "beforeExpr": false,
        "startsExpr": true,
        "rightAssociative": false,
        "isLoop": false,
        "isAssign": false,
        "prefix": false,
        "postfix": false,
        "binop": null
      },
      "value": "constructor",
      "start": 572,
      "end": 583,
      "loc": {
        "start": {
          "line": 17,
          "column": 2
        },
        "end": {
          "line": 17,
          "column": 13
        }
      }
    },
    {
      "type": {
        "label": "(",
        "beforeExpr": true,
        "startsExpr": true,
        "rightAssociative": false,
        "isLoop": false,
        "isAssign": false,
        "prefix": false,
        "postfix": false,
        "binop": null
      },
      "start": 583,
      "end": 584,
      "loc": {
        "start": {
          "line": 17,
          "column": 13
        },
        "end": {
          "line": 17,
          "column": 14
        }
      }
    },
    {
      "type": {
        "label": "name",
        "beforeExpr": false,
        "startsExpr": true,
        "rightAssociative": false,
        "isLoop": false,
        "isAssign": false,
        "prefix": false,
        "postfix": false,
        "binop": null
      },
      "value": "name",
      "start": 584,
      "end": 588,
      "loc": {
        "start": {
          "line": 17,
          "column": 14
        },
        "end": {
          "line": 17,
          "column": 18
        }
      }
    },
    {
      "type": {
        "label": ",",
        "beforeExpr": true,
        "startsExpr": false,
        "rightAssociative": false,
        "isLoop": false,
        "isAssign": false,
        "prefix": false,
        "postfix": false,
        "binop": null,
        "updateContext": null
      },
      "start": 588,
      "end": 589,
      "loc": {
        "start": {
          "line": 17,
          "column": 18
        },
        "end": {
          "line": 17,
          "column": 19
        }
      }
    },
    {
      "type": {
        "label": "name",
        "beforeExpr": false,
        "startsExpr": true,
        "rightAssociative": false,
        "isLoop": false,
        "isAssign": false,
        "prefix": false,
        "postfix": false,
        "binop": null
      },
      "value": "id",
      "start": 590,
      "end": 592,
      "loc": {
        "start": {
          "line": 17,
          "column": 20
        },
        "end": {
          "line": 17,
          "column": 22
        }
      }
    },
    {
      "type": {
        "label": ",",
        "beforeExpr": true,
        "startsExpr": false,
        "rightAssociative": false,
        "isLoop": false,
        "isAssign": false,
        "prefix": false,
        "postfix": false,
        "binop": null,
        "updateContext": null
      },
      "start": 592,
      "end": 593,
      "loc": {
        "start": {
          "line": 17,
          "column": 22
        },
        "end": {
          "line": 17,
          "column": 23
        }
      }
    },
    {
      "type": {
        "label": "name",
        "beforeExpr": false,
        "startsExpr": true,
        "rightAssociative": false,
        "isLoop": false,
        "isAssign": false,
        "prefix": false,
        "postfix": false,
        "binop": null
      },
      "value": "count",
      "start": 594,
      "end": 599,
      "loc": {
        "start": {
          "line": 17,
          "column": 24
        },
        "end": {
          "line": 17,
          "column": 29
        }
      }
    },
    {
      "type": {
        "label": ",",
        "beforeExpr": true,
        "startsExpr": false,
        "rightAssociative": false,
        "isLoop": false,
        "isAssign": false,
        "prefix": false,
        "postfix": false,
        "binop": null,
        "updateContext": null
      },
      "start": 599,
      "end": 600,
      "loc": {
        "start": {
          "line": 17,
          "column": 29
        },
        "end": {
          "line": 17,
          "column": 30
        }
      }
    },
    {
      "type": {
        "label": "name",
        "beforeExpr": false,
        "startsExpr": true,
        "rightAssociative": false,
        "isLoop": false,
        "isAssign": false,
        "prefix": false,
        "postfix": false,
        "binop": null
      },
      "value": "ability",
      "start": 601,
      "end": 608,
      "loc": {
        "start": {
          "line": 17,
          "column": 31
        },
        "end": {
          "line": 17,
          "column": 38
        }
      }
    },
    {
      "type": {
        "label": ",",
        "beforeExpr": true,
        "startsExpr": false,
        "rightAssociative": false,
        "isLoop": false,
        "isAssign": false,
        "prefix": false,
        "postfix": false,
        "binop": null,
        "updateContext": null
      },
      "start": 608,
      "end": 609,
      "loc": {
        "start": {
          "line": 17,
          "column": 38
        },
        "end": {
          "line": 17,
          "column": 39
        }
      }
    },
    {
      "type": {
        "label": "name",
        "beforeExpr": false,
        "startsExpr": true,
        "rightAssociative": false,
        "isLoop": false,
        "isAssign": false,
        "prefix": false,
        "postfix": false,
        "binop": null
      },
      "value": "abilityLevel",
      "start": 610,
      "end": 622,
      "loc": {
        "start": {
          "line": 17,
          "column": 40
        },
        "end": {
          "line": 17,
          "column": 52
        }
      }
    },
    {
      "type": {
        "label": ")",
        "beforeExpr": false,
        "startsExpr": false,
        "rightAssociative": false,
        "isLoop": false,
        "isAssign": false,
        "prefix": false,
        "postfix": false,
        "binop": null
      },
      "start": 622,
      "end": 623,
      "loc": {
        "start": {
          "line": 17,
          "column": 52
        },
        "end": {
          "line": 17,
          "column": 53
        }
      }
    },
    {
      "type": {
        "label": "{",
        "beforeExpr": true,
        "startsExpr": true,
        "rightAssociative": false,
        "isLoop": false,
        "isAssign": false,
        "prefix": false,
        "postfix": false,
        "binop": null
      },
      "start": 624,
      "end": 625,
      "loc": {
        "start": {
          "line": 17,
          "column": 54
        },
        "end": {
          "line": 17,
          "column": 55
        }
      }
    },
    {
      "type": {
        "label": "super",
        "keyword": "super",
        "beforeExpr": false,
        "startsExpr": true,
        "rightAssociative": false,
        "isLoop": false,
        "isAssign": false,
        "prefix": false,
        "postfix": false,
        "binop": null,
        "updateContext": null
      },
      "value": "super",
      "start": 630,
      "end": 635,
      "loc": {
        "start": {
          "line": 18,
          "column": 4
        },
        "end": {
          "line": 18,
          "column": 9
        }
      }
    },
    {
      "type": {
        "label": "(",
        "beforeExpr": true,
        "startsExpr": true,
        "rightAssociative": false,
        "isLoop": false,
        "isAssign": false,
        "prefix": false,
        "postfix": false,
        "binop": null
      },
      "start": 635,
      "end": 636,
      "loc": {
        "start": {
          "line": 18,
          "column": 9
        },
        "end": {
          "line": 18,
          "column": 10
        }
      }
    },
    {
      "type": {
        "label": "name",
        "beforeExpr": false,
        "startsExpr": true,
        "rightAssociative": false,
        "isLoop": false,
        "isAssign": false,
        "prefix": false,
        "postfix": false,
        "binop": null
      },
      "value": "name",
      "start": 636,
      "end": 640,
      "loc": {
        "start": {
          "line": 18,
          "column": 10
        },
        "end": {
          "line": 18,
          "column": 14
        }
      }
    },
    {
      "type": {
        "label": ",",
        "beforeExpr": true,
        "startsExpr": false,
        "rightAssociative": false,
        "isLoop": false,
        "isAssign": false,
        "prefix": false,
        "postfix": false,
        "binop": null,
        "updateContext": null
      },
      "start": 640,
      "end": 641,
      "loc": {
        "start": {
          "line": 18,
          "column": 14
        },
        "end": {
          "line": 18,
          "column": 15
        }
      }
    },
    {
      "type": {
        "label": "name",
        "beforeExpr": false,
        "startsExpr": true,
        "rightAssociative": false,
        "isLoop": false,
        "isAssign": false,
        "prefix": false,
        "postfix": false,
        "binop": null
      },
      "value": "id",
      "start": 642,
      "end": 644,
      "loc": {
        "start": {
          "line": 18,
          "column": 16
        },
        "end": {
          "line": 18,
          "column": 18
        }
      }
    },
    {
      "type": {
        "label": ",",
        "beforeExpr": true,
        "startsExpr": false,
        "rightAssociative": false,
        "isLoop": false,
        "isAssign": false,
        "prefix": false,
        "postfix": false,
        "binop": null,
        "updateContext": null
      },
      "start": 644,
      "end": 645,
      "loc": {
        "start": {
          "line": 18,
          "column": 18
        },
        "end": {
          "line": 18,
          "column": 19
        }
      }
    },
    {
      "type": {
        "label": "name",
        "beforeExpr": false,
        "startsExpr": true,
        "rightAssociative": false,
        "isLoop": false,
        "isAssign": false,
        "prefix": false,
        "postfix": false,
        "binop": null
      },
      "value": "count",
      "start": 646,
      "end": 651,
      "loc": {
        "start": {
          "line": 18,
          "column": 20
        },
        "end": {
          "line": 18,
          "column": 25
        }
      }
    },
    {
      "type": {
        "label": ",",
        "beforeExpr": true,
        "startsExpr": false,
        "rightAssociative": false,
        "isLoop": false,
        "isAssign": false,
        "prefix": false,
        "postfix": false,
        "binop": null,
        "updateContext": null
      },
      "start": 651,
      "end": 652,
      "loc": {
        "start": {
          "line": 18,
          "column": 25
        },
        "end": {
          "line": 18,
          "column": 26
        }
      }
    },
    {
      "type": {
        "label": "name",
        "beforeExpr": false,
        "startsExpr": true,
        "rightAssociative": false,
        "isLoop": false,
        "isAssign": false,
        "prefix": false,
        "postfix": false,
        "binop": null
      },
      "value": "ability",
      "start": 653,
      "end": 660,
      "loc": {
        "start": {
          "line": 18,
          "column": 27
        },
        "end": {
          "line": 18,
          "column": 34
        }
      }
    },
    {
      "type": {
        "label": ",",
        "beforeExpr": true,
        "startsExpr": false,
        "rightAssociative": false,
        "isLoop": false,
        "isAssign": false,
        "prefix": false,
        "postfix": false,
        "binop": null,
        "updateContext": null
      },
      "start": 660,
      "end": 661,
      "loc": {
        "start": {
          "line": 18,
          "column": 34
        },
        "end": {
          "line": 18,
          "column": 35
        }
      }
    },
    {
      "type": {
        "label": "name",
        "beforeExpr": false,
        "startsExpr": true,
        "rightAssociative": false,
        "isLoop": false,
        "isAssign": false,
        "prefix": false,
        "postfix": false,
        "binop": null
      },
      "value": "abilityLevel",
      "start": 662,
      "end": 674,
      "loc": {
        "start": {
          "line": 18,
          "column": 36
        },
        "end": {
          "line": 18,
          "column": 48
        }
      }
    },
    {
      "type": {
        "label": ")",
        "beforeExpr": false,
        "startsExpr": false,
        "rightAssociative": false,
        "isLoop": false,
        "isAssign": false,
        "prefix": false,
        "postfix": false,
        "binop": null
      },
      "start": 674,
      "end": 675,
      "loc": {
        "start": {
          "line": 18,
          "column": 48
        },
        "end": {
          "line": 18,
          "column": 49
        }
      }
    },
    {
      "type": {
        "label": ";",
        "beforeExpr": true,
        "startsExpr": false,
        "rightAssociative": false,
        "isLoop": false,
        "isAssign": false,
        "prefix": false,
        "postfix": false,
        "binop": null,
        "updateContext": null
      },
      "start": 675,
      "end": 676,
      "loc": {
        "start": {
          "line": 18,
          "column": 49
        },
        "end": {
          "line": 18,
          "column": 50
        }
      }
    },
    {
      "type": "CommentBlock",
      "value": "*\n     * Reference to the items dictionary for stat lookups\n     * @type {Object}\n     ",
      "start": 681,
      "end": 772,
      "loc": {
        "start": {
          "line": 19,
          "column": 4
        },
        "end": {
          "line": 22,
          "column": 7
        }
      }
    },
    {
      "type": {
        "label": "this",
        "keyword": "this",
        "beforeExpr": false,
        "startsExpr": true,
        "rightAssociative": false,
        "isLoop": false,
        "isAssign": false,
        "prefix": false,
        "postfix": false,
        "binop": null,
        "updateContext": null
      },
      "value": "this",
      "start": 777,
      "end": 781,
      "loc": {
        "start": {
          "line": 23,
          "column": 4
        },
        "end": {
          "line": 23,
          "column": 8
        }
      }
    },
    {
      "type": {
        "label": ".",
        "beforeExpr": false,
        "startsExpr": false,
        "rightAssociative": false,
        "isLoop": false,
        "isAssign": false,
        "prefix": false,
        "postfix": false,
        "binop": null,
        "updateContext": null
      },
      "start": 781,
      "end": 782,
      "loc": {
        "start": {
          "line": 23,
          "column": 8
        },
        "end": {
          "line": 23,
          "column": 9
        }
      }
    },
    {
      "type": {
        "label": "name",
        "beforeExpr": false,
        "startsExpr": true,
        "rightAssociative": false,
        "isLoop": false,
        "isAssign": false,
        "prefix": false,
        "postfix": false,
        "binop": null
      },
      "value": "itemsDictionary",
      "start": 782,
      "end": 797,
      "loc": {
        "start": {
          "line": 23,
          "column": 9
        },
        "end": {
          "line": 23,
          "column": 24
        }
      }
    },
    {
      "type": {
        "label": "=",
        "beforeExpr": true,
        "startsExpr": false,
        "rightAssociative": false,
        "isLoop": false,
        "isAssign": true,
        "prefix": false,
        "postfix": false,
        "binop": null,
        "updateContext": null
      },
      "value": "=",
      "start": 798,
      "end": 799,
      "loc": {
        "start": {
          "line": 23,
          "column": 25
        },
        "end": {
          "line": 23,
          "column": 26
        }
      }
    },
    {
      "type": {
        "label": "name",
        "beforeExpr": false,
        "startsExpr": true,
        "rightAssociative": false,
        "isLoop": false,
        "isAssign": false,
        "prefix": false,
        "postfix": false,
        "binop": null
      },
      "value": "ItemsDictionary",
      "start": 800,
      "end": 815,
      "loc": {
        "start": {
          "line": 23,
          "column": 27
        },
        "end": {
          "line": 23,
          "column": 42
        }
      }
    },
    {
      "type": {
        "label": ";",
        "beforeExpr": true,
        "startsExpr": false,
        "rightAssociative": false,
        "isLoop": false,
        "isAssign": false,
        "prefix": false,
        "postfix": false,
        "binop": null,
        "updateContext": null
      },
      "start": 815,
      "end": 816,
      "loc": {
        "start": {
          "line": 23,
          "column": 42
        },
        "end": {
          "line": 23,
          "column": 43
        }
      }
    },
    {
      "type": "CommentBlock",
      "value": "*\n     * The pendant level used to calculate the amplifier\n     * @type {Number}\n     ",
      "start": 821,
      "end": 911,
      "loc": {
        "start": {
          "line": 24,
          "column": 4
        },
        "end": {
          "line": 27,
          "column": 7
        }
      }
    },
    {
      "type": {
        "label": "this",
        "keyword": "this",
        "beforeExpr": false,
        "startsExpr": true,
        "rightAssociative": false,
        "isLoop": false,
        "isAssign": false,
        "prefix": false,
        "postfix": false,
        "binop": null,
        "updateContext": null
      },
      "value": "this",
      "start": 916,
      "end": 920,
      "loc": {
        "start": {
          "line": 28,
          "column": 4
        },
        "end": {
          "line": 28,
          "column": 8
        }
      }
    },
    {
      "type": {
        "label": ".",
        "beforeExpr": false,
        "startsExpr": false,
        "rightAssociative": false,
        "isLoop": false,
        "isAssign": false,
        "prefix": false,
        "postfix": false,
        "binop": null,
        "updateContext": null
      },
      "start": 920,
      "end": 921,
      "loc": {
        "start": {
          "line": 28,
          "column": 8
        },
        "end": {
          "line": 28,
          "column": 9
        }
      }
    },
    {
      "type": {
        "label": "name",
        "beforeExpr": false,
        "startsExpr": true,
        "rightAssociative": false,
        "isLoop": false,
        "isAssign": false,
        "prefix": false,
        "postfix": false,
        "binop": null
      },
      "value": "pendantLevel",
      "start": 921,
      "end": 933,
      "loc": {
        "start": {
          "line": 28,
          "column": 9
        },
        "end": {
          "line": 28,
          "column": 21
        }
      }
    },
    {
      "type": {
        "label": "=",
        "beforeExpr": true,
        "startsExpr": false,
        "rightAssociative": false,
        "isLoop": false,
        "isAssign": true,
        "prefix": false,
        "postfix": false,
        "binop": null,
        "updateContext": null
      },
      "value": "=",
      "start": 934,
      "end": 935,
      "loc": {
        "start": {
          "line": 28,
          "column": 22
        },
        "end": {
          "line": 28,
          "column": 23
        }
      }
    },
    {
      "type": {
        "label": "this",
        "keyword": "this",
        "beforeExpr": false,
        "startsExpr": true,
        "rightAssociative": false,
        "isLoop": false,
        "isAssign": false,
        "prefix": false,
        "postfix": false,
        "binop": null,
        "updateContext": null
      },
      "value": "this",
      "start": 936,
      "end": 940,
      "loc": {
        "start": {
          "line": 28,
          "column": 24
        },
        "end": {
          "line": 28,
          "column": 28
        }
      }
    },
    {
      "type": {
        "label": ".",
        "beforeExpr": false,
        "startsExpr": false,
        "rightAssociative": false,
        "isLoop": false,
        "isAssign": false,
        "prefix": false,
        "postfix": false,
        "binop": null,
        "updateContext": null
      },
      "start": 940,
      "end": 941,
      "loc": {
        "start": {
          "line": 28,
          "column": 28
        },
        "end": {
          "line": 28,
          "column": 29
        }
      }
    },
    {
      "type": {
        "label": "name",
        "beforeExpr": false,
        "startsExpr": true,
        "rightAssociative": false,
        "isLoop": false,
        "isAssign": false,
        "prefix": false,
        "postfix": false,
        "binop": null
      },
      "value": "itemsDictionary",
      "start": 941,
      "end": 956,
      "loc": {
        "start": {
          "line": 28,
          "column": 29
        },
        "end": {
          "line": 28,
          "column": 44
        }
      }
    },
    {
      "type": {
        "label": ".",
        "beforeExpr": false,
        "startsExpr": false,
        "rightAssociative": false,
        "isLoop": false,
        "isAssign": false,
        "prefix": false,
        "postfix": false,
        "binop": null,
        "updateContext": null
      },
      "start": 956,
      "end": 957,
      "loc": {
        "start": {
          "line": 28,
          "column": 44
        },
        "end": {
          "line": 28,
          "column": 45
        }
      }
    },
    {
      "type": {
        "label": "name",
        "beforeExpr": false,
        "startsExpr": true,
        "rightAssociative": false,
        "isLoop": false,
        "isAssign": false,
        "prefix": false,
        "postfix": false,
        "binop": null
      },
      "value": "getPendantLevel",
      "start": 957,
      "end": 972,
      "loc": {
        "start": {
          "line": 28,
          "column": 45
        },
        "end": {
          "line": 28,
          "column": 60
        }
      }
    },
    {
      "type": {
        "label": "(",
        "beforeExpr": true,
        "startsExpr": true,
        "rightAssociative": false,
        "isLoop": false,
        "isAssign": false,
        "prefix": false,
        "postfix": false,
        "binop": null
      },
      "start": 972,
      "end": 973,
      "loc": {
        "start": {
          "line": 28,
          "column": 60
        },
        "end": {
          "line": 28,
          "column": 61
        }
      }
    },
    {
      "type": {
        "label": "name",
        "beforeExpr": false,
        "startsExpr": true,
        "rightAssociative": false,
        "isLoop": false,
        "isAssign": false,
        "prefix": false,
        "postfix": false,
        "binop": null
      },
      "value": "name",
      "start": 973,
      "end": 977,
      "loc": {
        "start": {
          "line": 28,
          "column": 61
        },
        "end": {
          "line": 28,
          "column": 65
        }
      }
    },
    {
      "type": {
        "label": ")",
        "beforeExpr": false,
        "startsExpr": false,
        "rightAssociative": false,
        "isLoop": false,
        "isAssign": false,
        "prefix": false,
        "postfix": false,
        "binop": null
      },
      "start": 977,
      "end": 978,
      "loc": {
        "start": {
          "line": 28,
          "column": 65
        },
        "end": {
          "line": 28,
          "column": 66
        }
      }
    },
    {
      "type": {
        "label": ";",
        "beforeExpr": true,
        "startsExpr": false,
        "rightAssociative": false,
        "isLoop": false,
        "isAssign": false,
        "prefix": false,
        "postfix": false,
        "binop": null,
        "updateContext": null
      },
      "start": 978,
      "end": 979,
      "loc": {
        "start": {
          "line": 28,
          "column": 66
        },
        "end": {
          "line": 28,
          "column": 67
        }
      }
    },
    {
      "type": {
        "label": "}",
        "beforeExpr": false,
        "startsExpr": false,
        "rightAssociative": false,
        "isLoop": false,
        "isAssign": false,
        "prefix": false,
        "postfix": false,
        "binop": null
      },
      "start": 982,
      "end": 983,
      "loc": {
        "start": {
          "line": 29,
          "column": 2
        },
        "end": {
          "line": 29,
          "column": 3
        }
      }
    },
    {
      "type": "CommentBlock",
      "value": "*\n   * Returns the base stat amplifier provided by this pendant\n   * @return {Number}\n   ",
      "start": 987,
      "end": 1080,
      "loc": {
        "start": {
          "line": 31,
          "column": 2
        },
        "end": {
          "line": 34,
          "column": 5
        }
      }
    },
    {
      "type": {
        "label": "name",
        "beforeExpr": false,
        "startsExpr": true,
        "rightAssociative": false,
        "isLoop": false,
        "isAssign": false,
        "prefix": false,
        "postfix": false,
        "binop": null
      },
      "value": "getBaseAmplifier",
      "start": 1083,
      "end": 1099,
      "loc": {
        "start": {
          "line": 35,
          "column": 2
        },
        "end": {
          "line": 35,
          "column": 18
        }
      }
    },
    {
      "type": {
        "label": "(",
        "beforeExpr": true,
        "startsExpr": true,
        "rightAssociative": false,
        "isLoop": false,
        "isAssign": false,
        "prefix": false,
        "postfix": false,
        "binop": null
      },
      "start": 1099,
      "end": 1100,
      "loc": {
        "start": {
          "line": 35,
          "column": 18
        },
        "end": {
          "line": 35,
          "column": 19
        }
      }
    },
    {
      "type": {
        "label": ")",
        "beforeExpr": false,
        "startsExpr": false,
        "rightAssociative": false,
        "isLoop": false,
        "isAssign": false,
        "prefix": false,
        "postfix": false,
        "binop": null
      },
      "start": 1100,
      "end": 1101,
      "loc": {
        "start": {
          "line": 35,
          "column": 19
        },
        "end": {
          "line": 35,
          "column": 20
        }
      }
    },
    {
      "type": {
        "label": "{",
        "beforeExpr": true,
        "startsExpr": true,
        "rightAssociative": false,
        "isLoop": false,
        "isAssign": false,
        "prefix": false,
        "postfix": false,
        "binop": null
      },
      "start": 1102,
      "end": 1103,
      "loc": {
        "start": {
          "line": 35,
          "column": 21
        },
        "end": {
          "line": 35,
          "column": 22
        }
      }
    },
    {
      "type": {
        "label": "return",
        "keyword": "return",
        "beforeExpr": true,
        "startsExpr": false,
        "rightAssociative": false,
        "isLoop": false,
        "isAssign": false,
        "prefix": false,
        "postfix": false,
        "binop": null,
        "updateContext": null
      },
      "value": "return",
      "start": 1108,
      "end": 1114,
      "loc": {
        "start": {
          "line": 36,
          "column": 4
        },
        "end": {
          "line": 36,
          "column": 10
        }
      }
    },
    {
      "type": {
        "label": "num",
        "beforeExpr": false,
        "startsExpr": true,
        "rightAssociative": false,
        "isLoop": false,
        "isAssign": false,
        "prefix": false,
        "postfix": false,
        "binop": null,
        "updateContext": null
      },
      "value": 1,
      "start": 1115,
      "end": 1118,
      "loc": {
        "start": {
          "line": 36,
          "column": 11
        },
        "end": {
          "line": 36,
          "column": 14
        }
      }
    },
    {
      "type": {
        "label": "+/-",
        "beforeExpr": true,
        "startsExpr": true,
        "rightAssociative": false,
        "isLoop": false,
        "isAssign": false,
        "prefix": true,
        "postfix": false,
        "binop": 9,
        "updateContext": null
      },
      "value": "+",
      "start": 1119,
      "end": 1120,
      "loc": {
        "start": {
          "line": 36,
          "column": 15
        },
        "end": {
          "line": 36,
          "column": 16
        }
      }
    },
    {
      "type": {
        "label": "this",
        "keyword": "this",
        "beforeExpr": false,
        "startsExpr": true,
        "rightAssociative": false,
        "isLoop": false,
        "isAssign": false,
        "prefix": false,
        "postfix": false,
        "binop": null,
        "updateContext": null
      },
      "value": "this",
      "start": 1121,
      "end": 1125,
      "loc": {
        "start": {
          "line": 36,
          "column": 17
        },
        "end": {
          "line": 36,
          "column": 21
        }
      }
    },
    {
      "type": {
        "label": ".",
        "beforeExpr": false,
        "startsExpr": false,
        "rightAssociative": false,
        "isLoop": false,
        "isAssign": false,
        "prefix": false,
        "postfix": false,
        "binop": null,
        "updateContext": null
      },
      "start": 1125,
      "end": 1126,
      "loc": {
        "start": {
          "line": 36,
          "column": 21
        },
        "end": {
          "line": 36,
          "column": 22
        }
      }
    },
    {
      "type": {
        "label": "name",
        "beforeExpr": false,
        "startsExpr": true,
        "rightAssociative": false,
        "isLoop": false,
        "isAssign": false,
        "prefix": false,
        "postfix": false,
        "binop": null
      },
      "value": "pendantLevel",
      "start": 1126,
      "end": 1138,
      "loc": {
        "start": {
          "line": 36,
          "column": 22
        },
        "end": {
          "line": 36,
          "column": 34
        }
      }
    },
    {
      "type": {
        "label": "/",
        "beforeExpr": true,
        "startsExpr": false,
        "rightAssociative": false,
        "isLoop": false,
        "isAssign": false,
        "prefix": false,
        "postfix": false,
        "binop": 10,
        "updateContext": null
      },
      "value": "/",
      "start": 1139,
      "end": 1140,
      "loc": {
        "start": {
          "line": 36,
          "column": 35
        },
        "end": {
          "line": 36,
          "column": 36
        }
      }
    },
    {
      "type": {
        "label": "num",
        "beforeExpr": false,
        "startsExpr": true,
        "rightAssociative": false,
        "isLoop": false,
        "isAssign": false,
        "prefix": false,
        "postfix": false,
        "binop": null,
        "updateContext": null
      },
      "value": 100,
      "start": 1141,
      "end": 1144,
      "loc": {
        "start": {
          "line": 36,
          "column": 37
        },
        "end": {
          "line": 36,
          "column": 40
        }
      }
    },
    {
      "type": {
        "label": ";",
        "beforeExpr": true,
        "startsExpr": false,
        "rightAssociative": false,
        "isLoop": false,
        "isAssign": false,
        "prefix": false,
        "postfix": false,
        "binop": null,
        "updateContext": null
      },
      "start": 1144,
      "end": 1145,
      "loc": {
        "start": {
          "line": 36,
          "column": 40
        },
        "end": {
          "line": 36,
          "column": 41
        }
      }
    },
    {
      "type": {
        "label": "}",
        "beforeExpr": false,
        "startsExpr": false,
        "rightAssociative": false,
        "isLoop": false,
        "isAssign": false,
        "prefix": false,
        "postfix": false,
        "binop": null
      },
      "start": 1148,
      "end": 1149,
      "loc": {
        "start": {
          "line": 37,
          "column": 2
        },
        "end": {
          "line": 37,
          "column": 3
        }
      }
    },
    {
      "type": {
        "label": "}",
        "beforeExpr": false,
        "startsExpr": false,
        "rightAssociative": false,
        "isLoop": false,
        "isAssign": false,
        "prefix": false,
        "postfix": false,
        "binop": null
      },
      "start": 1150,
      "end": 1151,
      "loc": {
        "start": {
          "line": 38,
          "column": 0
        },
        "end": {
          "line": 38,
          "column": 1
        }
      }
    },
    {
      "type": {
        "label": "eof",
        "beforeExpr": false,
        "startsExpr": false,
        "rightAssociative": false,
        "isLoop": false,
        "isAssign": false,
        "prefix": false,
        "postfix": false,
        "binop": null,
        "updateContext": null
      },
      "start": 1152,
      "end": 1152,
      "loc": {
        "start": {
          "line": 39,
          "column": 0
        },
        "end": {
          "line": 39,
          "column": 0
        }
      }
    }
  ]
}